<?xml version="1.0" encoding="UTF-8" standalone="yes"?><imgdir name="01142527.img"><imgdir name="info"><canvas name="icon" width="33" height="32"><vector name="origin" x="0" y="32"/><string name="_hash" value="ec4edcd33e5ede0b983f597940ffcabf88ca8b3e4214bbe03bdb9d039f2b56be"/></canvas><canvas name="iconRaw" width="33" height="32"><vector name="origin" x="0" y="32"/><string name="_hash" value="f99dd2a6eb2917a1e4e91f5d67316364d960a355e1a1ff035467fff67c050844"/></canvas><string name="islot" value="Me"/><string name="vslot" value="Me"/><int name="tuc" value="0"/><int name="reqJob" value="0"/><int name="reqLevel" value="140"/><long name="incPAD" value="1"/><long name="incMAD" value="1"/><int name="incACC" value="60"/><int name="charmEXP" value="100"/><int name="cash" value="0"/><int name="only" value="1"/><int name="medalTag" value="391"/><int name="price" value="30000"/><int name="equipTradeBlock" value="1"/><int name="tradeAvailable" value="2"/><imgdir name="level"><imgdir name="info"><imgdir name="1"><int name="exp" value="10000"/></imgdir><imgdir name="2"><int name="exp" value="10000"/></imgdir><imgdir name="3"><int name="exp" value="10000"/></imgdir><imgdir name="4"><int name="exp" value="10000"/></imgdir><imgdir name="5"><int name="exp" value="10000"/></imgdir><imgdir name="6"><int name="exp" value="10000"/></imgdir><imgdir name="7"><int name="exp" value="10000"/></imgdir><imgdir name="8"><int name="exp" value="10000"/></imgdir><imgdir name="9"><int name="exp" value="10000"/></imgdir><imgdir name="10"><int name="exp" value="10000"/></imgdir><imgdir name="11"><int name="exp" value="10000"/></imgdir><imgdir name="12"><int name="exp" value="10000"/></imgdir><imgdir name="13"><int name="exp" value="10000"/></imgdir><imgdir name="14"><int name="exp" value="10000"/></imgdir><imgdir name="15"><int name="exp" value="10000"/></imgdir><imgdir name="16"><int name="exp" value="10000"/></imgdir><imgdir name="17"><int name="exp" value="10000"/></imgdir><imgdir name="18"><int name="exp" value="10000"/></imgdir><imgdir name="19"><int name="exp" value="10000"/></imgdir><imgdir name="20"><int name="exp" value="10000"/></imgdir><imgdir name="21"><int name="exp" value="10000"/></imgdir><imgdir name="22"><int name="exp" value="10000"/></imgdir><imgdir name="23"><int name="exp" value="10000"/></imgdir><imgdir name="24"><int name="exp" value="10000"/></imgdir><imgdir name="25"><int name="exp" value="10000"/></imgdir><imgdir name="26"><int name="exp" value="10000"/></imgdir><imgdir name="27"><int name="exp" value="10000"/></imgdir><imgdir name="28"><int name="exp" value="10000"/></imgdir><imgdir name="29"><int name="exp" value="10000"/></imgdir><imgdir name="30"><int name="exp" value="10000"/></imgdir></imgdir></imgdir></imgdir></imgdir>